mesh_atc/__init__.py
mesh_atc/defaults.py
mesh_atc/main.py
mesh_atc/lib/__init__.py
mesh_atc/lib/atc_pb2.py
mesh_atc-0.0.3.dist-info/LICENSE
mesh_atc-0.0.3.dist-info/METADATA
mesh_atc-0.0.3.dist-info/WHEEL
mesh_atc-0.0.3.dist-info/top_level.txt
mesh_atc-0.0.3.dist-info/RECORD
